garfetch/__init__.py
garfetch-0.2.0.dist-info/LICENSE
garfetch-0.2.0.dist-info/WHEEL
garfetch-0.2.0.dist-info/METADATA
garfetch-0.2.0.dist-info/RECORD
