Metadata-Version: 2.1
Name: garfetch
Version: 0.2.0
Summary: Unofficial gocomics library
Home-page: https://gitlab.com/a/garfetch
License: MIT
Author: Ave
Author-email: ave@ave.zone
Requires-Python: >=3.6,<4.0
Classifier: License :: OSI Approved :: MIT License
Classifier: Programming Language :: Python :: 3
Classifier: Programming Language :: Python :: 3.6
Classifier: Programming Language :: Python :: 3.7
Classifier: Programming Language :: Python :: 3.8
Classifier: Programming Language :: Python :: 3.9
Requires-Dist: beautifulsoup4 (>=4.9.3,<5.0.0)
Requires-Dist: requests (>=2.25.1,<3.0.0)
Project-URL: Repository, https://gitlab.com/a/garfetch
